_librabbitmq.so
funtests/__init__.py
funtests/config.py
funtests/disabled_basic_get_leak.py
funtests/setup.py
funtests/tests/__init__.py
funtests/tests/test_channel_errors.py
librabbitmq/__init__.py
librabbitmq/tests/__init__.py
librabbitmq/tests/test_functional.py
librabbitmq-1.6.1.dist-info/DESCRIPTION.rst
librabbitmq-1.6.1.dist-info/METADATA
librabbitmq-1.6.1.dist-info/metadata.json
librabbitmq-1.6.1.dist-info/RECORD
librabbitmq-1.6.1.dist-info/top_level.txt
librabbitmq-1.6.1.dist-info/WHEEL
