Metadata-Version: 1.1
Name: librabbitmq
Version: 1.6.1
Summary: AMQP Client using the rabbitmq-c library.
Home-page: http://github.com/celery/librabbitmq
Author: Ask Solem
Author-email: ask@celeryproject.org
License: MPL
Platform: UNKNOWN
Classifier: Development Status :: 5 - Production/Stable
Classifier: Operating System :: POSIX
Classifier: Operating System :: Microsoft :: Windows
Classifier: Programming Language :: C
Classifier: Programming Language :: Python :: 2.5
Classifier: Programming Language :: Python :: 2.6
Classifier: Programming Language :: Python :: 2.7
Classifier: Programming Language :: Python :: Implementation :: CPython
Classifier: Intended Audience :: Developers
Classifier: License :: OSI Approved :: Mozilla Public License 1.0 (MPL)
Classifier: Topic :: Communications
Classifier: Topic :: System :: Networking
Classifier: Topic :: Software Development :: Libraries
